ut_models_api/__init__.py
ut_models_api/py.typed
ut_models_api/user_beers.py
ut_models_api/user_friends.py
ut_models_api/user_info.py
ut_models_api-0.1.2.dist-info/METADATA
ut_models_api-0.1.2.dist-info/WHEEL
ut_models_api-0.1.2.dist-info/RECORD
